README.md
setup.py
TimeExtral_advanced_8d2/__init__.py
TimeExtral_advanced_8d2.egg-info/PKG-INFO
TimeExtral_advanced_8d2.egg-info/SOURCES.txt
TimeExtral_advanced_8d2.egg-info/dependency_links.txt
TimeExtral_advanced_8d2.egg-info/requires.txt
TimeExtral_advanced_8d2.egg-info/top_level.txt