Metadata-Version: 2.1
Name: TimeExtral-advanced-8d2
Version: 0.1.0
Summary: Time but better
Home-page: https://github.com/huangyingw/borisbabic-browser_cookie3
Author: Paul
Author-email: PW668878@outlook.com
Classifier: Development Status :: 3 - Alpha
Classifier: Intended Audience :: Developers
Classifier: License :: OSI Approved :: GNU Lesser General Public License v3 or later (LGPLv3+)
Classifier: Programming Language :: Python :: 3
Classifier: Programming Language :: Python :: 3.6
Classifier: Programming Language :: Python :: 3.7
Classifier: Programming Language :: Python :: 3.8
Classifier: Programming Language :: Python :: 3.9
Classifier: Topic :: Software Development :: Libraries :: Python Modules
